pyECLAT/__init__.py
pyECLAT/__main__.py
pyECLAT/pyECLAT.py
pyECLAT-1.0.2.dist-info/LICENSE
pyECLAT-1.0.2.dist-info/METADATA
pyECLAT-1.0.2.dist-info/WHEEL
pyECLAT-1.0.2.dist-info/top_level.txt
pyECLAT-1.0.2.dist-info/RECORD
