Metadata-Version: 2.1
Name: pyECLAT
Version: 1.0.2
Summary: A package for association analysis using the ECLAT method.
Home-page: https://github.com/jeffrichardchemistry/pyECLAT
Author: Jefferson Richard
Author-email: jrichardquimica@gmail.com
License: BSD License
Keywords: Data Science ECLAT Association statistic Artificial intelligence
Platform: UNKNOWN
Classifier: Intended Audience :: Developers
Classifier: Intended Audience :: End Users/Desktop
Classifier: Intended Audience :: Science/Research
Classifier: License :: OSI Approved :: BSD License
Classifier: Natural Language :: English
Classifier: Operating System :: Unix
Classifier: Operating System :: Microsoft :: Windows
Classifier: Operating System :: MacOS
Classifier: Topic :: Scientific/Engineering :: Artificial Intelligence
Classifier: Programming Language :: Python
Classifier: Programming Language :: Python :: 3
Classifier: Programming Language :: Python :: 3.6
Requires-Dist: pandas (>=0.25.3)
Requires-Dist: numpy (>=1.17.4)
Requires-Dist: tqdm (>=4.41.1)
